mozdef_client/__init__.py
mozdef_client/asset_hint.py
mozdef_client/compliance.py
mozdef_client/error.py
mozdef_client/event.py
mozdef_client/message.py
mozdef_client/msg.py
mozdef_client/rra.py
mozdef_client/vulnerability.py
mozdef_client-1.1.dist-info/AUTHORS.rst
mozdef_client-1.1.dist-info/LICENSE
mozdef_client-1.1.dist-info/METADATA
mozdef_client-1.1.dist-info/WHEEL
mozdef_client-1.1.dist-info/top_level.txt
mozdef_client-1.1.dist-info/RECORD
