Metadata-Version: 2.1
Name: mozdef-client
Version: 1.1
Summary: A client library to send messages/events using MozDef This package is built upon commit 208536a8f1e128eade433afe9fe18d76438de97e
Home-page: https://github.com/mozilla/mozdef_client
Author: Guillaume Destuynder
Author-email: gdestuynder@mozilla.com
License: MPL
Keywords: mozdef client library
Platform: UNKNOWN
Classifier: Development Status :: 5 - Production/Stable
Classifier: Topic :: Software Development :: Libraries :: Python Modules
Classifier: Topic :: System :: Logging
Classifier: License :: OSI Approved :: Mozilla Public License 2.0 (MPL 2.0)
Classifier: Natural Language :: English
Classifier: Programming Language :: Python
Classifier: Programming Language :: Python :: 2
Classifier: Programming Language :: Python :: 2.7
Classifier: Programming Language :: Python :: 3
Classifier: Programming Language :: Python :: 3.4
Classifier: Programming Language :: Python :: 3.5
Classifier: Programming Language :: Python :: 3.6
Classifier: Programming Language :: Python :: 3.7
License-File: LICENSE
License-File: AUTHORS.rst
Requires-Dist: requests-futures
Requires-Dist: pytz
Requires-Dist: boto3
